README.rst
setup.py
IPOperations/__init__.py
IPOperations/asr_lists.py
IPOperations/isr_lists.py
Prefix_list_Ops.egg-info/PKG-INFO
Prefix_list_Ops.egg-info/SOURCES.txt
Prefix_list_Ops.egg-info/dependency_links.txt
Prefix_list_Ops.egg-info/requires.txt
Prefix_list_Ops.egg-info/top_level.txt