Metadata-Version: 2.1
Name: Prefix-list-Ops
Version: 1.0.0
Summary: Perform operations on network prefix-list
Home-page: https://github.com/cober2019/Network-Automation/tree/master/NETCONF-YANG/Prefix-List_Ops
Author: Chris Oberdalhoff
Author-email: cober91130@gmail.com
License: UNKNOWN
Platform: UNKNOWN
Classifier: Programming Language :: Python :: 3
Classifier: License :: OSI Approved :: MIT License
Classifier: Operating System :: OS Independent
Requires-Python: >=3.6
